LICENSE
README.md
setup.cfg
setup.py
autofd/__init__.py
autofd/general_array.py
autofd/general_array_test.py
autofd/utils.py
autofd.egg-info/PKG-INFO
autofd.egg-info/SOURCES.txt
autofd.egg-info/dependency_links.txt
autofd.egg-info/requires.txt
autofd.egg-info/top_level.txt
autofd/operators/__init__.py
autofd/operators/operators.py
autofd/operators/operators_test.py
autofd/operators/transforms.py