Metadata-Version: 2.1
Name: autofd
Version: 0.0.9
Summary: "Automatic Functional Derivative in JAX"
Home-page: https://github.com/sail-sg/autofd
Author: "Min Lin"
Author-email: "linmin@sea.com"
Project-URL: Bug Tracker, https://github.com/sail-sg/autofd/issues
Classifier: Programming Language :: Python :: 3
Requires-Python: >=3.10
License-File: LICENSE
